nnu_mcp/NNU_MCP.py
nnu_mcp/app.py
nnu_mcp/main.py
nnu_mcp-0.1.0.dist-info/METADATA
nnu_mcp-0.1.0.dist-info/WHEEL
nnu_mcp-0.1.0.dist-info/entry_points.txt
nnu_mcp-0.1.0.dist-info/RECORD
